test_pypi_pru-0.1.0.dist-info/WHEEL
test_pypi_pru-0.1.0.dist-info/METADATA
test_pypi_pru-0.1.0.dist-info/RECORD
test_pypi_pru/main.py
test_pypi_pru/test_pypi_pru_main.so
test_pypi_pru/__init__.py
test_pypi_pru/sub2/modulo2.py
test_pypi_pru/sub2/test_pypi_pru_sub2_modulo2.so
test_pypi_pru/sub2/__init__.py
test_pypi_pru/sub1/modulo1.py
test_pypi_pru/sub1/test_pypi_pru_sub1_modulo1.so
test_pypi_pru/sub1/__init__.py
