Metadata-Version: 2.2
Name: test_pypi_pru
Version: 0.1.0
Summary: Proyecto compilado con Cython (Binarios solamente). Proyecto empaquetado con scikit-build-core y setuptools
Requires-Python: >=3.8
Requires-Dist: pandas
Requires-Dist: numpy
